mindt_Selino/__init__.py
mindt_Selino/dtMinOptimized.py
mindt_Selino/dtMinimisation.py
mindt_Selino/optimizedQuineMcCluskey.py
mindt_Selino/quineMcCluskey.py
mindt_Selino/Implicant/__init__.py
mindt_Selino/Implicant/booleanImplicant.py
mindt_Selino/Implicant/implicant.py
mindt_Selino/Implicant/intervalmplicant.py
mindt_Selino/Implicant/optimizedintervalImplicant.py
mindt_Selino/Resources/__init__.py
mindt_Selino/Resources/intervalsGenerator.py
mindt_Selino/Resources/readInput.py
mindt_Selino/Resources/resources.py
mindt_selino-0.1.2.dist-info/METADATA
mindt_selino-0.1.2.dist-info/WHEEL
mindt_selino-0.1.2.dist-info/licenses/LICENSE
mindt_selino-0.1.2.dist-info/RECORD
