Metadata-Version: 2.1
Name: mindt_Selino
Version: 0.1.2
Summary: This package allow to minimize the output from a given Decision Tree.
Project-URL: Homepage, https://github.com/AbelJuncal/DTMinimisation
Project-URL: Issues, https://github.com/AbelJuncal/DTMinimisation/issues
Author-email: Abel Juncal Suárez <abeljuncalsuarez@gmail.com>
License-Expression: MPL-2.0
License-File: LICENSE
Classifier: Operating System :: OS Independent
Classifier: Programming Language :: Python :: 3
Requires-Python: >=3.8
Requires-Dist: matplotlib
Requires-Dist: pandas
Requires-Dist: seaborn
